sanydata/__init__.py
sanydata/datatools.py
sanydata/model_data_message_pb2.py
sanydata/model_data_message_pb2_grpc.py
utils/__init__.py
utils/cos_handler.py
utils/env_helper.py
utils/file_operation.py
utils/local_handler.py
sanydata-3.3.13.dist-info/METADATA
sanydata-3.3.13.dist-info/WHEEL
sanydata-3.3.13.dist-info/top_level.txt
sanydata-3.3.13.dist-info/RECORD
