Metadata-Version: 2.1
Name: sanydata
Version: 3.3.13
Summary: get data and get wind farm information
Home-page: http://gitlab.sanywind.net/sanydata/sanydata
Author: thao
Author-email: thao92@126.com
License: MIT Licence
Keywords: pip,sanydata,thao
Platform: any
Requires-Dist: grpcio
Requires-Dist: grpcio-tools
Requires-Dist: gql
Requires-Dist: pandas
Requires-Dist: elasticsearch
Requires-Dist: requests
Requires-Dist: requests-toolbelt
Requires-Dist: cos-python-sdk-v5
Requires-Dist: pyarrow
Requires-Dist: hdfs
Requires-Dist: python-logstash
Requires-Dist: sentry-sdk
Requires-Dist: protobuf (==3.19.0)
